[
{
    "category": "Сайдинг",
    "name": "Фиброцементный сайдинг красный ГОСТ 18124-2012",
    "price": "630",
    "unit": "₽",
    "characteristics": {
        "Производитель": "Тимлюйский шифер",
        "Тип сайдинга": "Фиброцементный",
        "Толщина": "8 мм",
        "Применение": "Для наружной отделки",
        "Ударная вязкость, кгс/см2": "3,9",
        "Морозостойкость": "F25",
        "Дугостойкость при токе 20 мА, с": "30",
        "Электрическая прочность, кВ/м": "20x10^3",
        "Предел прочности при изгибе, МПА (кгс/см2)": "264",
        "Габариты (В х Ш х Г)": "8 × 220 × 3000 мм",
        "Площадь листа, м2": "0,66",
        "Объемный вес, г/см3": "1,69",
        "Штук в поддоне": "252"
    },
    "link": "https://baza.124bt.ru/product/fibrocementnyy-sayding-krasnyy-gost-18124-2012/",
    "resource": "https://baza.124bt.ru",
    "date_time": "2025-04-18 02:23:26"
},
{
    "category": "Ступени железобетонные",
    "name": "Ступень железобетонная ЛС 23-1",
    "price": "2 774",
    "unit": "₽",
    "characteristics": {
        "Габариты (В х Ш х Г)": "2250 × 380 × 187 мм",
        "Вес": "250 кг",
        "Производитель": "КБС",
        "Объем": "0.1 м³",
        "Марка прочности": "М200"
    },
    "link": "https://baza.124bt.ru/product/stupen-zhelezobetonnaya-ls-23-1/",
    "resource": "https://baza.124bt.ru",
    "date_time": "2025-04-18 02:23:26"
},
{
    "category": "Лотки железобетонные",
    "name": "Лоток для прокладки трубопроводов Л34-8",
    "price": "40 500",
    "unit": "₽",
    "characteristics": {
        "Габариты (В х Ш х Г)": "1680 × 3380 × 2970 мм",
        "Вес": "7730 кг",
        "Производитель": "БТ",
        "Объем": "3.09 м³"
    },
    "link": "https://baza.124bt.ru/product/lotok-dlya-prokladki-truboprovodov-l34-8/",
    "resource": "https://baza.124bt.ru",
    "date_time": "2025-04-18 02:23:26"
},
{
    "category": "ЖБИ септики",
    "name": "Бетонный септик объемом 1.41 м.куб",
    "price": "13 500",
    "unit": "₽",
    "characteristics": {
        "Объем": "1.41 м³",
        "Материал": "железобетонный",
        "Строение": "однокамерный",
        "Глубина": "285 см",
        "Назначение": "для дачи ,  для туалета",
        "Количество колодцев": "1",
        "Количество человек": "до 2 человек",
        "Вес": "1078 кг",
        "Производитель": "БТ"
    },
    "link": "https://baza.124bt.ru/product/betonnyy-septik-obemom-141-mkub/",
    "resource": "https://baza.124bt.ru",
    "date_time": "2025-04-18 02:23:26"
}
]
